{
  "model_type": "Logistic Regression",
  "features": [
    "is_legit_sender",
    "sender_is_number",
    "sender_length",
    "suspicious_sender_name",
    "has_link",
    "link_count",
    "has_legit_domain",
    "has_fraud_shortener",
    "has_typosquat_domain",
    "link_at_end",
    "link_at_start",
    "has_ussd_code",
    "ussd_code_count",
    "has_sms_shortcode",
    "sms_shortcode_count",
    "has_official_contact",
    "has_mobile_number",
    "mobile_number_count",
    "has_win_claim",
    "win_claim_count",
    "has_prize_amount",
    "max_prize_amount",
    "unrealistic_prize",
    "extreme_prize",
    "has_guarantee",
    "guarantee_count",
    "has_payment_request",
    "suspicious_fee_count",
    "has_suspicious_fee",
    "pay_to_claim_pattern",
    "urgency_count",
    "has_urgency",
    "high_urgency",
    "has_time_pressure",
    "mentions_expiration",
    "exclamation_count",
    "exclamation_density",
    "excessive_exclamations",
    "question_count",
    "caps_word_count",
    "excessive_caps",
    "emoji_count",
    "has_emoji",
    "message_length",
    "word_count",
    "safaricom_brand_count",
    "has_safaricom_brand",
    "mentions_terms",
    "says_stand_a_chance",
    "says_you_won",
    "mentions_optout",
    "hashtag_count",
    "has_hashtag",
    "says_dial",
    "has_sms_instruction",
    "has_click_bait",
    "requests_verification",
    "claims_authority",
    "fraud_pattern_count",
    "has_fraud_pattern",
    "win_fee_urgency_combo",
    "link_payment_combo",
    "unrealistic_prize_fee",
    "no_legit_contact_payment",
    "fraud_link_win_combo",
    "legitimacy_score",
    "high_legitimacy",
    "fraud_risk_score",
    "high_fraud_risk",
    "message_text"
  ],
  "feature_count": 70,
  "training_date": "2026-01-04T14:06:49.230187",
  "performance": {
    "accuracy": 0.983,
    "precision": 0.9777777777777777,
    "recall": 0.9801980198019802,
    "f1_score": 0.9789864029666254,
    "auc": 0.9832323783972358
  },
  "model_purpose": "promotion_fraud_detection"
}